picknmix/__init__.py
picknmix/cli.py
picknmix/picknmix.py
picknmix-0.1.3.dist-info/AUTHORS.rst
picknmix-0.1.3.dist-info/LICENSE
picknmix-0.1.3.dist-info/METADATA
picknmix-0.1.3.dist-info/WHEEL
picknmix-0.1.3.dist-info/entry_points.txt
picknmix-0.1.3.dist-info/top_level.txt
picknmix-0.1.3.dist-info/RECORD
