Metadata-Version: 2.1
Name: picknmix
Version: 0.1.3
Summary: A simple tool to help building stacking models.
Home-page: https://github.com/Cheukting/picknmix
Author: Cheuk Ting Ho
Author-email: cheukting.ho@gmail.com
License: MIT license
Keywords: picknmix
Platform: UNKNOWN
Classifier: Development Status :: 2 - Pre-Alpha
Classifier: Intended Audience :: Developers
Classifier: License :: OSI Approved :: MIT License
Classifier: Natural Language :: English
Classifier: Programming Language :: Python :: 3
Classifier: Programming Language :: Python :: 3.5
Classifier: Programming Language :: Python :: 3.6
Classifier: Programming Language :: Python :: 3.7
Requires-Python: >=3.5
Requires-Dist: Click (>=6.0)
Requires-Dist: scikit-learn (>=0.21.2)
